MANIFEST.in
README.md
setup.py
slitscan/__init__.py
slitscan/__main__.py
slitscan/slitscan.py
slitscan.egg-info/PKG-INFO
slitscan.egg-info/SOURCES.txt
slitscan.egg-info/dependency_links.txt
slitscan.egg-info/entry_points.txt
slitscan.egg-info/not-zip-safe
slitscan.egg-info/requires.txt
slitscan.egg-info/top_level.txt