Metadata-Version: 1.0
Name: slitscan
Version: 0.3.1
Summary: Slit-scan photography.
Home-page: http://github.com/markjarzynski/slitscan
Author: Mark Jarzynski
Author-email: mark.jarzynski@gmail.com
License: MIT
Platform: UNKNOWN
